prog03/asig.vhd
--asing.vhd recuerda llamar al archivo como a la entidad 24/10/2022
library IEEE;
use IEEE.STD_LOGIC_1164.ALL;
--Asgnaciones concurrentes "when -- else"
entity asig is
    Port ( a : in  STD_LOGIC;
           out1 : out  STD_LOGIC);
end asig;

architecture Behavioral of asig is
--Signals
--Compuerta not con "when--else"
begin
	out1 <= '0' when a='1' else
		    '1' when a='0'  ;
end Behavioral;

prog03/asig_tb.vhd
--asing_tb.vhd recuerda llamar al archivo como a la entidad 24/10/2022
LIBRARY ieee;
USE ieee.std_logic_1164.ALL;
--entidad tb
ENTITY asig_tb IS
END asig_tb;
---arquitectura del componente de la uut
architecture bhv of asig_tb is 
-- componente
component asig is
    port(
            a : in std_logic;
            out1 : out std_logic
        );
end component;
--señales
--Entrada
signal a : std_logic := '0';
--salida
signal out1 : std_logic;
--unidad de pruebas
begin uut: asig port map(
    a => a,
    out1 => out1
    );
--proceso de estimulos 
        stim: process
        begin
            wait for 10 ns;
            --insertar estimulos
            a <= '0'; wait for 10 ns; --0
            a <= '1'; wait for 10 ns; --1
            a <= '0'; wait for 10 ns; --0
            a <= '1'; wait for 10 ns; --1
            a <= '0'; wait for 10 ns; --0
            a <= '1'; wait for 10 ns; --1
            a <= '0'; wait for 10 ns; --0
            a <= '1'; wait for 10 ns; --1
            a <= '0'; wait for 10 ns; --0
            a <= '1'; wait for 10 ns; --1
            a <= '0'; wait for 10 ns; --0
            a <= '1'; wait for 10 ns; --1
            a <= '0'; wait for 10 ns; --0
            a <= '1'; wait for 10 ns; --1
            wait;
        end process;
end;

prog03/simu1.vcd
$date
  Mon Oct 24 22:20:29 2022
$end
$version
  GHDL v0
$end
$timescale
  1 fs
$end
$scope module standard $end
$upscope $end
$scope module std_logic_1164 $end
$upscope $end
$scope module asig_tb $end
$var reg 1 ! a $end
$var reg 1 " out1 $end
$scope module uut $end
$var reg 1 # a $end
$var reg 1 $ out1 $end
$upscope $end
$upscope $end
$enddefinitions $end
#0
0!
1"
0#
1$
#10000000
#20000000
1!
0"
1#
0$
#30000000
0!
1"
0#
1$
#40000000
1!
0"
1#
0$
#50000000
0!
1"
0#
1$
#60000000
1!
0"
1#
0$
#70000000
0!
1"
0#
1$
#80000000
1!
0"
1#
0$
#90000000
0!
1"
0#
1$
#100000000
1!
0"
1#
0$
#110000000
0!
1"
0#
1$
#120000000
1!
0"
1#
0$
#130000000
0!
1"
0#
1$
#140000000
1!
0"
1#
0$
