prog01/comb.vhd
--Encabezado lbreras
library IEEE;
use IEEE.STD_LOGIC_1164.ALL;

--ENTIDAD CTO DE CAJA NEGRA
entity comb is
    port(
            a : in std_logic;
            b : in std_logic;
            c : in std_logic;
            d : in std_logic;
            s,y : out std_logic
    );
end comb;
--Arquitectura es el comportamiento de CTO CN

architecture comportamiento  of comb is --falto is
--Señals signals 
    begin
    s <= (d nand b)or(not c)or((not b)and a)or(d and b and (not a));
    y <= ((not b)and(not a)) or (b and (not a)) or ((not d)and c); --dcba abcd
end comportamiento;

prog01/comb_tb.vhd
LIBRARY ieee;
USE ieee.std_logic_1164.ALL;

ENTITY comb_tb IS
END comb_tb;

---arquitectura del componente de la uut
architecture bhv of comb_tb is 
-- componente
component comb is
    port(
            a : in std_logic;
            b : in std_logic;
            c : in std_logic;
            d : in std_logic;
            s,y : out std_logic
        );
end component;
--señales
--Entrada
signal a : std_logic := '0';
signal b : std_logic := '0';
signal c : std_logic := '0';
signal d : std_logic := '0';
--salida
signal s,y : std_logic;
--unidad de pruebas
begin uut: comb port map(
    a => a,
    b => b,
    c => c,
    d => d,
    s => s,
    y => y
    );
--proceso de estimulos 
        stim: process
        begin
            wait for 100 ns;
            --insertar estimulos
            d <= '0'; c <= '0';b <= '0';a <= '0'; wait for 100 ns; --0
            d <= '0'; c <= '0';b <= '0';a <= '1'; wait for 100 ns; --1
            d <= '0'; c <= '0';b <= '1';a <= '0'; wait for 100 ns; --2
            d <= '0'; c <= '0';b <= '1';a <= '1'; wait for 100 ns; --3
            d <= '0'; c <= '1';b <= '0';a <= '0'; wait for 100 ns; --4
            d <= '0'; c <= '1';b <= '0';a <= '1'; wait for 100 ns; --5
            d <= '0'; c <= '1';b <= '1';a <= '0'; wait for 100 ns; --6
            d <= '0'; c <= '1';b <= '1';a <= '1'; wait for 100 ns; --7
            d <= '1'; c <= '0';b <= '0';a <= '0'; wait for 100 ns; --8
            d <= '1'; c <= '0';b <= '0';a <= '1'; wait for 100 ns; --9
            d <= '1'; c <= '0';b <= '1';a <= '0'; wait for 100 ns; --10
            d <= '1'; c <= '0';b <= '1';a <= '1'; wait for 100 ns; --11
            d <= '1'; c <= '1';b <= '0';a <= '0'; wait for 100 ns; --12
            d <= '1'; c <= '1';b <= '0';a <= '1'; wait for 100 ns; --13
            d <= '1'; c <= '1';b <= '1';a <= '0'; wait for 100 ns; --14
            d <= '1'; c <= '1';b <= '1';a <= '1'; wait for 100 ns; --15
            wait;
        end process;
end;

prog01/simu1.vcd
$date
  Fri Oct 14 23:14:46 2022
$end
$version
  GHDL v0
$end
$timescale
  1 fs
$end
$scope module standard $end
$upscope $end
$scope module std_logic_1164 $end
$upscope $end
$scope module comb_tb $end
$var reg 1 ! a $end
$var reg 1 " b $end
$var reg 1 # c $end
$var reg 1 $ d $end
$var reg 1 % s $end
$var reg 1 & y $end
$scope module uut $end
$var reg 1 ' a $end
$var reg 1 ( b $end
$var reg 1 ) c $end
$var reg 1 * d $end
$var reg 1 + s $end
$var reg 1 , y $end
$upscope $end
$upscope $end
$enddefinitions $end
#0
0!
0"
0#
0$
1%
1&
0'
0(
0)
0*
1+
1,
#100000000
#200000000
1!
0&
1'
0,
#300000000
0!
1"
1&
0'
1(
1,
#400000000
1!
0&
1'
0,
#500000000
0!
0"
1#
1&
0'
0(
1)
1,
#600000000
1!
1'
#700000000
0!
1"
0'
1(
#800000000
1!
1'
#900000000
0!
0"
0#
1$
0'
0(
0)
1*
#1000000000
1!
0&
1'
0,
#1100000000
0!
1"
1&
0'
1(
1,
#1200000000
1!
0&
1'
0,
#1300000000
0!
0"
1#
1&
0'
0(
1)
1,
#1400000000
1!
0&
1'
0,
#1500000000
0!
1"
1&
0'
1(
1,
#1600000000
1!
0%
0&
1'
0+
0,
