prog02/sign.vhd
-- vsg_off
--sing.vhd recuerda llamar al archivo como a la entidad 12/10/2022
--Encabezado lbreras
library IEEE;
use IEEE.STD_LOGIC_1164.ALL;
--ENTIDAD CTO DE CAJA NEGRA
entity sign is
    port(
            a : in std_logic;
            b : in std_logic;
            c : in std_logic;
            d : in std_logic;
            e : in std_logic;
            f : out std_logic
    );
end sign;
--Arquitectura es el comportamiento de CTO CN
architecture comportamiento  of sign is 
--Señals signals
signal sig1: std_logic; 
signal sig2: std_logic;
signal sig3: std_logic;
--Signal es una palabra clave de VHDL. Declara una señal del tipo de datos especificado. 
--Una declaración de señal se utiliza para representar señales internas dentro de una declaración de arquitectura.
begin
    sig1 <= a or b;
    sig2 <= d and c;
    sig3 <= sig1 and sig2;
    f <= sig3 or e ;
end comportamiento;

prog02/sign_tb.vhd
--sing_tb.vhd recuerda llamar al archivo como a la entidad 12/10/2022
LIBRARY ieee;
USE ieee.std_logic_1164.ALL;
--entidad tb
ENTITY sign_tb IS
END sign_tb;
---arquitectura del componente de la uut
architecture bhv of sign_tb is 
-- componente
component sign is
    port(
            a : in std_logic;
            b : in std_logic;
            c : in std_logic;
            d : in std_logic;
            e : in std_logic;
            f : out std_logic
        );
end component;
--señales
--Entrada
signal a : std_logic := '0';
signal b : std_logic := '0';
signal c : std_logic := '0';
signal d : std_logic := '0';
signal e : std_logic := '0';
--salida
signal f : std_logic;
--unidad de pruebas
begin uut: sign port map(
    a => a,
    b => b,
    c => c,
    d => d,
    e => e,
    f => f
    );
--proceso de estimulos 
        stim: process
        begin
            wait for 50 ns;
            --insertar estimulos
            e <= '0'; d <= '0'; c <= '0';b <= '0';a <= '0'; wait for 50 ns; --0
            e <= '0'; d <= '0'; c <= '0';b <= '0';a <= '1'; wait for 50 ns; --1
            e <= '0'; d <= '0'; c <= '0';b <= '1';a <= '0'; wait for 50 ns; --2
            e <= '0'; d <= '0'; c <= '0';b <= '1';a <= '1'; wait for 50 ns; --3
            e <= '0'; d <= '0'; c <= '1';b <= '0';a <= '0'; wait for 50 ns; --4
            e <= '0'; d <= '0'; c <= '1';b <= '0';a <= '1'; wait for 50 ns; --5
            e <= '0'; d <= '0'; c <= '1';b <= '1';a <= '0'; wait for 50 ns; --6
            e <= '0'; d <= '0'; c <= '1';b <= '1';a <= '1'; wait for 50 ns; --7
            e <= '0'; d <= '1'; c <= '0';b <= '0';a <= '0'; wait for 50 ns; --8
            e <= '0'; d <= '1'; c <= '0';b <= '0';a <= '1'; wait for 50 ns; --9
            e <= '0'; d <= '1'; c <= '0';b <= '1';a <= '0'; wait for 50 ns; --10
            e <= '0'; d <= '1'; c <= '0';b <= '1';a <= '1'; wait for 50 ns; --11
            e <= '0'; d <= '1'; c <= '1';b <= '0';a <= '0'; wait for 50 ns; --12
            e <= '0'; d <= '1'; c <= '1';b <= '0';a <= '1'; wait for 50 ns; --13
            e <= '0'; d <= '1'; c <= '1';b <= '1';a <= '0'; wait for 50 ns; --14
            e <= '0'; d <= '1'; c <= '1';b <= '1';a <= '1'; wait for 50 ns; --15
            e <= '1'; d <= '0'; c <= '0';b <= '0';a <= '0'; wait for 50 ns; --16
            e <= '1'; d <= '0'; c <= '0';b <= '0';a <= '1'; wait for 50 ns; --17
            e <= '1'; d <= '0'; c <= '0';b <= '1';a <= '0'; wait for 50 ns; --18
            e <= '1'; d <= '0'; c <= '0';b <= '1';a <= '1'; wait for 50 ns; --19
            e <= '1'; d <= '0'; c <= '1';b <= '0';a <= '0'; wait for 50 ns; --20
            e <= '1'; d <= '0'; c <= '1';b <= '0';a <= '1'; wait for 50 ns; --21
            e <= '1'; d <= '0'; c <= '1';b <= '1';a <= '0'; wait for 50 ns; --22
            e <= '1'; d <= '0'; c <= '1';b <= '1';a <= '1'; wait for 50 ns; --23
            e <= '1'; d <= '1'; c <= '0';b <= '0';a <= '0'; wait for 50 ns; --24
            e <= '1'; d <= '1'; c <= '0';b <= '0';a <= '1'; wait for 50 ns; --25
            e <= '1'; d <= '1'; c <= '0';b <= '1';a <= '0'; wait for 50 ns; --26
            e <= '1'; d <= '1'; c <= '0';b <= '1';a <= '1'; wait for 50 ns; --27
            e <= '1'; d <= '1'; c <= '1';b <= '0';a <= '0'; wait for 50 ns; --28
            e <= '1'; d <= '1'; c <= '1';b <= '0';a <= '1'; wait for 50 ns; --29
            e <= '1'; d <= '1'; c <= '1';b <= '1';a <= '0'; wait for 50 ns; --30
            e <= '1'; d <= '1'; c <= '1';b <= '1';a <= '1'; wait for 50 ns; --31
            wait;
        end process;
end;

prog02/simu1.vcd
$date
  Wed Oct 19 13:53:26 2022
$end
$version
  GHDL v0
$end
$timescale
  1 fs
$end
$scope module standard $end
$upscope $end
$scope module std_logic_1164 $end
$upscope $end
$scope module sign_tb $end
$var reg 1 ! a $end
$var reg 1 " b $end
$var reg 1 # c $end
$var reg 1 $ d $end
$var reg 1 % e $end
$var reg 1 & f $end
$scope module uut $end
$var reg 1 ' a $end
$var reg 1 ( b $end
$var reg 1 ) c $end
$var reg 1 * d $end
$var reg 1 + e $end
$var reg 1 , f $end
$var reg 1 - sig1 $end
$var reg 1 . sig2 $end
$var reg 1 / sig3 $end
$upscope $end
$upscope $end
$enddefinitions $end
#0
0!
0"
0#
0$
0%
0&
0'
0(
0)
0*
0+
0,
0-
0.
0/
#50000000
#100000000
1!
1'
1-
#150000000
0!
1"
0'
1(
#200000000
1!
1'
#250000000
0!
0"
1#
0'
0(
1)
0-
#300000000
1!
1'
1-
#350000000
0!
1"
0'
1(
#400000000
1!
1'
#450000000
0!
0"
0#
1$
0'
0(
0)
1*
0-
#500000000
1!
1'
1-
#550000000
0!
1"
0'
1(
#600000000
1!
1'
#650000000
0!
0"
1#
0'
0(
1)
0-
1.
#700000000
1!
1&
1'
1,
1-
1/
#750000000
0!
1"
0'
1(
#800000000
1!
1'
#850000000
0!
0"
0#
0$
1%
0'
0(
0)
0*
1+
0-
0.
0/
#900000000
1!
1'
1-
#950000000
0!
1"
0'
1(
#1000000000
1!
1'
#1050000000
0!
0"
1#
0'
0(
1)
0-
#1100000000
1!
1'
1-
#1150000000
0!
1"
0'
1(
#1200000000
1!
1'
#1250000000
0!
0"
0#
1$
0'
0(
0)
1*
0-
#1300000000
1!
1'
1-
#1350000000
0!
1"
0'
1(
#1400000000
1!
1'
#1450000000
0!
0"
1#
0'
0(
1)
0-
1.
#1500000000
1!
1'
1-
1/
#1550000000
0!
1"
0'
1(
#1600000000
1!
1'
